<?xml version="1.0" encoding="utf-8"?>
<AdSettings xmlns:xsi="http://www.w3.org/2001/XMLSchema-instance" xmlns:xsd="http://www.w3.org/2001/XMLSchema">
	<CultureDescriptors>
    <AdCultureDescriptor CultureName="en-US">
      <Probabilities Probability="30" AdType="AdDuplex" AppID="2859"/>
      <Probabilities AppID="1d59fb0a677336d8cd4cbd5c7c117f9d" AdType="MobFox" Probability="40" IsTest="false"/>
      <Probabilities AppID="DavideCleopadre_ClockAlarmNightLight_WP7" AdType="InnerActive" Probability="30"/>
      <Probabilities Probability="0" AdType="DefaultHouseAd" AppID="http://adrotator.apphb.com/SampleRemoteHouseAd.xaml"/>
    </AdCultureDescriptor>
    <AdCultureDescriptor CultureName="en-GB">
      <Probabilities Probability="30" AdType="AdDuplex" AppID="2859"/>
      <Probabilities AppID="1d59fb0a677336d8cd4cbd5c7c117f9d" AdType="MobFox" Probability="40" IsTest="false"/>
      <Probabilities AppID="DavideCleopadre_ClockAlarmNightLight_WP7" AdType="InnerActive" Probability="30"/>
      <Probabilities Probability="0" AdType="DefaultHouseAd" AppID="http://adrotator.apphb.com/SampleRemoteHouseAd.xaml"/>
    </AdCultureDescriptor>
    <AdCultureDescriptor CultureName="de-DE">
      <Probabilities Probability="30" AdType="AdDuplex" AppID="2859"/>
      <Probabilities AppID="1d59fb0a677336d8cd4cbd5c7c117f9d" AdType="MobFox" Probability="40" IsTest="false"/>
      <Probabilities AppID="DavideCleopadre_ClockAlarmNightLight_WP7" AdType="InnerActive" Probability="30"/>
      <Probabilities Probability="0" AdType="DefaultHouseAd" AppID="http://adrotator.apphb.com/SampleRemoteHouseAd.xaml"/>
    </AdCultureDescriptor>
	<AdCultureDescriptor CultureName="default">
      <Probabilities Probability="30" AdType="AdDuplex" AppID="2859"/>
      <Probabilities AppID="1d59fb0a677336d8cd4cbd5c7c117f9d" AdType="MobFox" Probability="40" IsTest="false"/>
      <Probabilities AppID="DavideCleopadre_ClockAlarmNightLight_WP7" AdType="InnerActive" Probability="30"/>
      <Probabilities Probability="0" AdType="DefaultHouseAd" AppID="http://adrotator.apphb.com/SampleRemoteHouseAd.xaml"/>
    </AdCultureDescriptor>
	</CultureDescriptors>
</AdSettings>
